contrastive/__init__.py
contrastive-1.0.0.dist-info/DESCRIPTION.rst
contrastive-1.0.0.dist-info/METADATA
contrastive-1.0.0.dist-info/RECORD
contrastive-1.0.0.dist-info/WHEEL
contrastive-1.0.0.dist-info/metadata.json
contrastive-1.0.0.dist-info/top_level.txt
