Metadata-Version: 2.0
Name: contrastive
Version: 1.0.0
Summary: Python library for performing unsupervised learning (e.g. PCA) in contrastive settings, where one is interested in finding directions and patterns that exist one dataset, but not the other
Home-page: https://github.com/abidlabs/contrastive
Author: Abubakar Abid
Author-email: a12d@stanford.edu
License: UNKNOWN
Keywords: unsupervised,contrastive,learning,PCA
Platform: UNKNOWN
Requires-Dist: matplotlib
Requires-Dist: numpy
Requires-Dist: sklearn
